{"cameraMode":{"drawMode":0,"name":"Shaded","section":"Shading Mode"},"sceneLighting":true,"audioPlay":false,"sceneViewState":{"showFog":true,"showMaterialUpdate":false,"showSkybox":true,"showFlares":true,"showImageEffects":true,"showParticleSystems":true},"in2DMode":false,"pivot":{"x":-37.71235656738281,"y":-15.586037635803223,"z":0.8697572946548462},"rotation":{"x":0.15139468014240266,"y":-0.6575281023979187,"z":0.13726896047592164,"w":0.7251880764961243},"size":60.86912536621094,"orthographic":false}